app/__init__.py
app/views.py
app/templates/index.html
app/tests/__init__.py
app/tests/test_app.py
demo_webapp-0.0.3.dist-info/LICENSE
demo_webapp-0.0.3.dist-info/METADATA
demo_webapp-0.0.3.dist-info/WHEEL
demo_webapp-0.0.3.dist-info/top_level.txt
demo_webapp-0.0.3.dist-info/RECORD
