Metadata-Version: 2.1
Name: demo-webapp
Version: 0.0.3
Summary: a simple web-app based on flask
Home-page: https://github.com/SebastienPittet/demo-webapp
Author: Sebastien Pittet
Author-email: sebastien@pittet.org
License: MIT
Keywords: demo exoscale
Platform: any
Classifier: Programming Language :: Python :: 3
Classifier: Programming Language :: Python :: 3.7
Classifier: Programming Language :: Python :: 3.6
Classifier: Programming Language :: Python :: 3.5
Classifier: Programming Language :: Python :: 3.4
Classifier: License :: OSI Approved :: MIT License
Classifier: Operating System :: OS Independent
Classifier: Development Status :: 3 - Alpha
Classifier: Intended Audience :: Developers
Classifier: Intended Audience :: Other Audience
License-File: LICENSE
Requires-Dist: Flask
Requires-Dist: requests
